README.txt
setup.py
pyramid_simpleform/__init__.py
pyramid_simpleform/renderers.py
pyramid_simpleform/tests.py
pyramid_simpleform_boldprogressives_fork.egg-info/PKG-INFO
pyramid_simpleform_boldprogressives_fork.egg-info/SOURCES.txt
pyramid_simpleform_boldprogressives_fork.egg-info/dependency_links.txt
pyramid_simpleform_boldprogressives_fork.egg-info/not-zip-safe
pyramid_simpleform_boldprogressives_fork.egg-info/requires.txt
pyramid_simpleform_boldprogressives_fork.egg-info/top_level.txt