Metadata-Version: 1.1
Name: pyramid-simpleform-boldprogressives-fork
Version: 0.7
Summary: pyramid_simpleform
Home-page: https://github.com/Pylons/pyramid_simpleform
Author: Chris Lambacher
Author-email: chris@kateandchris.net
License: LICENSE.txt
Keywords: web pyramid pylons
Platform: UNKNOWN
Classifier: Programming Language :: Python
Classifier: Framework :: Pylons
Classifier: Topic :: Internet :: WWW/HTTP
Classifier: Topic :: Internet :: WWW/HTTP :: WSGI :: Application
